uniTbrow/__init__.py
uniTbrow/constants/__init__.py
uniTbrow/constants/constants.py
uniTbrow/conversions/__init__.py
uniTbrow/conversions/base_unit_systems.py
uniTbrow/conversions/unit_conversions.py
uniTbrow/dimensions/__init__.py
uniTbrow/dimensions/dimensions.py
uniTbrow/parsers/__init__.py
uniTbrow/parsers/unit_parser.py
uniTbrow/units/__init__.py
uniTbrow/units/units.py
unitbrow-0.3.0.dist-info/METADATA
unitbrow-0.3.0.dist-info/WHEEL
unitbrow-0.3.0.dist-info/licenses/LICENSE
unitbrow-0.3.0.dist-info/RECORD
